<?xml version="1.0" encoding="UTF-8"?>
<billStatus>
  <bill>
    <cosponsors>
      <item>
        <firstName>BARBARA</firstName>
        <fullName>Rep. Lee, Barbara [D-CA-13]</fullName>
        <sponsorshipDate>2013-08-01</sponsorshipDate>
        <middleName />
        <bioguideId>L000551</bioguideId>
        <state>CA</state>
        <identifiers>
          <lisID>1501</lisID>
          <gpoId>7814</gpoId>
          <bioguideId>L000551</bioguideId>
        </identifiers>
        <sponsorshipWithdrawnDate />
        <isOriginalCosponsor>True</isOriginalCosponsor>
        <lastName>LEE</lastName>
        <district>13</district>
        <party>D</party>
      </item>
      <item>
        <firstName>ELEANOR</firstName>
        <fullName>Rep. Norton, Eleanor Holmes [D-DC-At Large]</fullName>
        <sponsorshipDate>2013-08-01</sponsorshipDate>
        <middleName>HOLMES</middleName>
        <bioguideId>N000147</bioguideId>
        <state>DC</state>
        <identifiers>
          <bioguideId>N000147</bioguideId>
          <lisID>868</lisID>
          <gpoId>7871</gpoId>
        </identifiers>
        <sponsorshipWithdrawnDate />
        <isOriginalCosponsor>True</isOriginalCosponsor>
        <lastName>NORTON</lastName>
        <district>0</district>
        <party>D</party>
      </item>
      <item>
        <firstName>TIM</firstName>
        <fullName>Rep. Ryan, Tim [D-OH-13]</fullName>
        <sponsorshipDate>2013-09-11</sponsorshipDate>
        <middleName />
        <bioguideId>R000577</bioguideId>
        <state>OH</state>
        <identifiers>
          <gpoId>8107</gpoId>
          <lisID>1756</lisID>
          <bioguideId>R000577</bioguideId>
        </identifiers>
        <sponsorshipWithdrawnDate />
        <isOriginalCosponsor>False</isOriginalCosponsor>
        <lastName>RYAN</lastName>
        <district>13</district>
        <party>D</party>
      </item>
    </cosponsors>
    <calendarNumbers />
    <titles>
      <item>
        <parentTitleType />
        <chamberCode />
        <chamberName />
        <title>International Women's Freedom Act of 2013</title>
        <titleType>Short Titles as Introduced</titleType>
      </item>
      <item>
        <parentTitleType />
        <chamberCode />
        <chamberName />
        <title>To express United States foreign policy with respect to, and to strengthen United States advocacy on behalf of, individuals persecuted and denied their rights in foreign countries on account of gender, and for other purposes.</title>
        <titleType>Official Title as Introduced</titleType>
      </item>
      <item>
        <parentTitleType />
        <chamberCode />
        <chamberName />
        <title>International Women's Freedom Act of 2013</title>
        <titleType>Display Title</titleType>
      </item>
    </titles>
    <notes />
    <sponsors>
      <item>
        <party>D</party>
        <fullName>Rep. Maloney, Carolyn B. [D-NY-12]</fullName>
        <firstName>CAROLYN</firstName>
        <byRequestType />
        <bioguideId>M000087</bioguideId>
        <district>12</district>
        <state>NY</state>
        <identifiers>
          <bioguideId>M000087</bioguideId>
          <gpoId>8075</gpoId>
          <lisID>729</lisID>
        </identifiers>
        <middleName>B.</middleName>
        <lastName>MALONEY</lastName>
      </item>
    </sponsors>
    <constitutionalAuthorityStatementText><![CDATA[<pre>By Mrs. CAROLYN B. MALONEY of New York:H.R. 2947.Congress has the power to enact this legislation pursuantto the following:Article 1, Section 8, Clause 3, which reads: ``To regulateCommerce with foreign Nations, and among the several States,and with Indian Tribes.''[Page H5346]</pre>]]></constitutionalAuthorityStatementText>
    <latestAction>
      <text>Referred to the Subcommittee on Immigration and Border Security.</text>
      <links />
      <actionDate>2013-09-13</actionDate>
    </latestAction>
    <title>International Women's Freedom Act of 2013</title>
    <actions>
      <actionByCounts>
        <houseOfRepresentatives>8</houseOfRepresentatives>
      </actionByCounts>
      <item>
        <actionDate>2013-09-13</actionDate>
        <committee>
          <systemCode>hsju01</systemCode>
          <name>Immigration and Border Security Subcommittee</name>
        </committee>
        <links />
        <sourceSystem>
          <code>1</code>
          <name>House committee actions</name>
        </sourceSystem>
        <text>Referred to the Subcommittee on Immigration and Border Security.</text>
        <type>Committee</type>
      </item>
      <item>
        <actionDate>2013-08-16</actionDate>
        <committee>
          <systemCode>hsfa16</systemCode>
          <name>Africa, Global Health, Global Human Rights and International Organizations Subcommittee</name>
        </committee>
        <links />
        <sourceSystem>
          <code>1</code>
          <name>House committee actions</name>
        </sourceSystem>
        <text>Referred to the Subcommittee on Africa, Global Health, Global Human Rights and International Organizations.</text>
        <type>Committee</type>
      </item>
      <item>
        <committee>
          <systemCode>hsju00</systemCode>
          <name>Judiciary Committee</name>
        </committee>
        <sourceSystem>
          <code>2</code>
          <name>House floor actions</name>
        </sourceSystem>
        <text>Referred to House Judiciary</text>
        <actionCode>H11100</actionCode>
        <actionDate>2013-08-01</actionDate>
        <links />
        <type>IntroReferral</type>
      </item>
      <item>
        <committee>
          <systemCode>hsba00</systemCode>
          <name>Financial Services Committee</name>
        </committee>
        <sourceSystem>
          <code>2</code>
          <name>House floor actions</name>
        </sourceSystem>
        <text>Referred to House Financial Services</text>
        <actionCode>H11100</actionCode>
        <actionDate>2013-08-01</actionDate>
        <links />
        <type>IntroReferral</type>
      </item>
      <item>
        <committee />
        <sourceSystem>
          <code>9</code>
          <name>Library of Congress</name>
        </sourceSystem>
        <text>Referred to the Committee on Foreign Affairs, and in addition to the Committees on Financial Services, and the Judiciary, for a period to be subsequently determined by the Speaker, in each case for consideration of such provisions as fall within the jurisdiction of the committee concerned.</text>
        <actionCode>H11100-A</actionCode>
        <actionDate>2013-08-01</actionDate>
        <links />
        <type>IntroReferral</type>
      </item>
      <item>
        <committee>
          <systemCode>hsfa00</systemCode>
          <name>Foreign Affairs Committee</name>
        </committee>
        <sourceSystem>
          <code>2</code>
          <name>House floor actions</name>
        </sourceSystem>
        <text>Referred to House Foreign Affairs</text>
        <actionCode>H11100</actionCode>
        <actionDate>2013-08-01</actionDate>
        <links />
        <type>IntroReferral</type>
      </item>
      <item>
        <committee />
        <sourceSystem>
          <code>9</code>
          <name>Library of Congress</name>
        </sourceSystem>
        <text>Sponsor introductory remarks on measure. (CR E1200)</text>
        <actionCode>B00100</actionCode>
        <actionDate>2013-08-01</actionDate>
        <links>
          <link>
            <url>https://www.congress.gov/congressional-record/volume-159/extensions-of-remarks-section/page/E1200</url>
            <name>E1200</name>
          </link>
        </links>
        <type>IntroReferral</type>
      </item>
      <item>
        <committee />
        <sourceSystem>
          <code>9</code>
          <name>Library of Congress</name>
        </sourceSystem>
        <text>Introduced in House</text>
        <actionCode>Intro-H</actionCode>
        <actionDate>2013-08-01</actionDate>
        <links />
        <type>IntroReferral</type>
      </item>
      <item>
        <committee />
        <sourceSystem>
          <code>9</code>
          <name>Library of Congress</name>
        </sourceSystem>
        <text>Introduced in House</text>
        <actionCode>1000</actionCode>
        <actionDate>2013-08-01</actionDate>
        <links />
        <type>IntroReferral</type>
      </item>
      <actionTypeCounts>
        <placeholderTextForH>2</placeholderTextForH>
        <billReferralsAggregate>1</billReferralsAggregate>
        <placeholderTextForB>1</placeholderTextForB>
        <introducedInTheHouse>1</introducedInTheHouse>
        <billReferrals>3</billReferrals>
        <introducedInHouse>1</introducedInHouse>
      </actionTypeCounts>
    </actions>
    <updateDate>2016-10-25T16:06:42Z</updateDate>
    <billType>HR</billType>
    <originChamber>House</originChamber>
    <committees>
      <billCommittees>
        <item>
          <type>Standing</type>
          <name>Judiciary Committee</name>
          <activities>
            <item>
              <date>2013-08-01T14:07:30Z</date>
              <name>Referred to</name>
            </item>
          </activities>
          <chamber>House</chamber>
          <subcommittees>
            <item>
              <activities>
                <item>
                  <date>2013-09-13T19:09:32Z</date>
                  <name>Referred to</name>
                </item>
              </activities>
              <systemCode>hsju01</systemCode>
              <name>Immigration and Border Security Subcommittee</name>
            </item>
          </subcommittees>
          <systemCode>hsju00</systemCode>
        </item>
        <item>
          <type>Standing</type>
          <name>Foreign Affairs Committee</name>
          <activities>
            <item>
              <date>2013-08-01T14:07:20Z</date>
              <name>Referred to</name>
            </item>
          </activities>
          <chamber>House</chamber>
          <subcommittees>
            <item>
              <activities>
                <item>
                  <date>2013-08-16T12:46:33Z</date>
                  <name>Referred to</name>
                </item>
              </activities>
              <systemCode>hsfa16</systemCode>
              <name>Africa, Global Health, Global Human Rights and International Organizations Subcommittee</name>
            </item>
          </subcommittees>
          <systemCode>hsfa00</systemCode>
        </item>
        <item>
          <type>Standing</type>
          <name>Financial Services Committee</name>
          <activities>
            <item>
              <date>2013-08-01T14:07:25Z</date>
              <name>Referred to</name>
            </item>
          </activities>
          <chamber>House</chamber>
          <subcommittees />
          <systemCode>hsba00</systemCode>
        </item>
      </billCommittees>
    </committees>
    <recordedVotes />
    <amendments />
    <laws />
    <introducedDate>2013-08-01</introducedDate>
    <billNumber>2947</billNumber>
    <policyArea>
      <name>International Affairs</name>
    </policyArea>
    <cboCostEstimates />
    <subjects>
      <billSubjects>
        <legislativeSubjects>
          <item>
            <name>Advisory bodies</name>
          </item>
          <item>
            <name>Business ethics</name>
          </item>
          <item>
            <name>Department of State</name>
          </item>
          <item>
            <name>Diplomacy, foreign officials, Americans abroad</name>
          </item>
          <item>
            <name>Employment discrimination and employee rights</name>
          </item>
          <item>
            <name>Executive Office of the President</name>
          </item>
          <item>
            <name>Executive agency funding and structure</name>
          </item>
          <item>
            <name>Foreign aid and international relief</name>
          </item>
          <item>
            <name>Government information and archives</name>
          </item>
          <item>
            <name>Human rights</name>
          </item>
          <item>
            <name>International organizations and cooperation</name>
          </item>
          <item>
            <name>Refugees, asylum, displaced persons</name>
          </item>
          <item>
            <name>Sanctions</name>
          </item>
          <item>
            <name>Sex, gender, sexual orientation discrimination</name>
          </item>
          <item>
            <name>Trade restrictions</name>
          </item>
          <item>
            <name>U.S. and foreign investments</name>
          </item>
          <item>
            <name>Women's rights</name>
          </item>
        </legislativeSubjects>
        <policyArea>
          <name>International Affairs</name>
        </policyArea>
      </billSubjects>
    </subjects>
    <committeeReports />
    <congress>113</congress>
    <createDate>2013-08-02T05:52:40Z</createDate>
    <relatedBills />
    <summaries>
      <billSummaries>
        <item>
          <actionDate>2013-08-01</actionDate>
          <actionDesc>Introduced in House</actionDesc>
          <versionCode>00</versionCode>
          <lastSummaryUpdateDate>2013-09-11T16:31:19Z</lastSummaryUpdateDate>
          <text><![CDATA[<p>International Women's Freedom Act of 2013 - Establishes within the Department of State an Office of International Women's Rights to be headed by an Ambassador at Large for International Women's Rights.</p> <p>Directs the Secretary of State to establish a women's rights Internet site and maintain prisoner lists and issue briefs on women's rights concerns.</p> <p>Amends the Foreign Service Act of 1980 to include instruction on the internationally recognized rights of women and the various aspects and manifestations of violations of women's rights in Foreign Service officer training.</p> <p>Establishes the United States Commission on International Women's Rights.</p> <p>Directs the President to take specified actions in response to women's rights violations, especially particularly severe rights violations.</p> <p>Prescribes criteria for the prohibition of economic, multilateral, military, and export assistance in instances of particularly severe women's rights violations.</p> <p>Prescribes requirements for the promotion of women's rights.</p> <p>Requires women's rights-related training with respect to refugee, asylum, and consular matters.</p> <p>Amends the Immigration and Nationality Act to declare inadmissible to the United States any foreign government officials who have engaged in particularly severe women's rights violations.</p> <p>Expresses the sense of Congress that: (1) transnational corporations operating overseas should adopt codes of conduct upholding the rights of their female employees, and (2) there should be within the staff of the National Security Council a Special Adviser to the President on International Women's Rights.</p>]]></text>
          <name>Introduced in House</name>
          <updateDate>2013-08-01T04:00:00Z</updateDate>
        </item>
      </billSummaries>
    </summaries>
  </bill>
  <dublinCore xmlns:dc="http://purl.org/dc/elements/1.1/">
    <dc:format>text/xml</dc:format>
    <dc:language>EN</dc:language>
    <dc:rights>Pursuant to Title 17 Section 105 of the United States Code, this file is not subject to copyright protection and is in the public domain.</dc:rights>
    <dc:contributor>Congressional Research Service, Library of Congress</dc:contributor>
    <dc:description>This file contains bill summaries and statuses for federal legislation. A bill summary describes the most significant provisions of a piece of legislation and details the effects the legislative text may have on current law and federal programs. Bill summaries are authored by the Congressional Research Service (CRS) of the Library of Congress. As stated in Public Law 91-510 (2 USC 166 (d)(6)), one of the duties of CRS is "to prepare summaries and digests of bills and resolutions of a public general nature introduced in the Senate or House of Representatives". For more information, refer to the User Guide that accompanies this file.</dc:description>
  </dublinCore>
</billStatus>

