<?xml version="1.0" encoding="UTF-8"?>
<billStatus>
  <bill>
    <subjects>
      <billSubjects>
        <policyArea>
          <name>Armed Forces and National Security</name>
        </policyArea>
        <legislativeSubjects>
          <item>
            <name>Appropriations</name>
          </item>
          <item>
            <name>Budget deficits and national debt</name>
          </item>
          <item>
            <name>Defense spending</name>
          </item>
          <item>
            <name>Department of Defense</name>
          </item>
          <item>
            <name>Government employee pay, benefits, personnel management</name>
          </item>
          <item>
            <name>Intelligence activities, surveillance, classified information</name>
          </item>
        </legislativeSubjects>
      </billSubjects>
    </subjects>
    <latestAction>
      <actionDate>2013-05-06</actionDate>
      <text>Referred to the Subcommittee on Readiness.</text>
      <links />
    </latestAction>
    <constitutionalAuthorityStatementText><![CDATA[<pre>[Congressional Record Volume 159, Number 53 (Thursday, April 18, 2013)]From the Congressional Record Online through the Government Publishing Office [<a href='http://www.gpo.gov'>www.gpo.gov</a>]By Mr. KILMER:H.R. 1642.Congress has the power to enact this legislation pursuantto the following:Article I, Section 8, Clause 1: The Congress shall havePower to lay and collect Taxes, Duties, Imposts and Excises,to pay the Debts and provide for the common Defence andgeneral Welfare of the United States; but all Duties, Impostsand Excises shall be uniform throughout the United States.Article I, Section 8, Clause 14: To make Rules for theGovernment and Regulation of the land and naval Forces.[Page H2160]</pre>]]></constitutionalAuthorityStatementText>
    <version>1.0.0</version>
    <sponsors>
      <item>
        <firstName>Derek</firstName>
        <identifiers>
          <bioguideId>K000381</bioguideId>
          <lisID>2169</lisID>
          <gpoId />
        </identifiers>
        <byRequestType />
        <state>WA</state>
        <fullName>Rep. Kilmer, Derek [D-WA-6]</fullName>
        <bioguideId>K000381</bioguideId>
        <middleName />
        <district>6</district>
        <lastName>Kilmer</lastName>
        <party>D</party>
      </item>
    </sponsors>
    <summaries>
      <billSummaries>
        <item>
          <versionCode>00</versionCode>
          <lastSummaryUpdateDate>2013-05-22T19:53:29Z</lastSummaryUpdateDate>
          <updateDate>2013-04-18T04:00:00Z</updateDate>
          <text><![CDATA[<p>Security Clearance Protection Act of 2013 - Requires the Secretary of Defense (DOD) to ensure that any financial hardship incurred by a DOD civilian employee due to a furlough required by sequestration will not affect such employee's: (1) eligibility for continued suitability for employment at DOD, (2) access to classified information, or (3) suitability to hold a position critical to national security.</p>]]></text>
          <actionDesc>Introduced in House</actionDesc>
          <name>Introduced in House</name>
          <actionDate>2013-04-18</actionDate>
        </item>
      </billSummaries>
    </summaries>
    <billType>HR</billType>
    <committees>
      <billCommittees>
        <item>
          <chamber>House</chamber>
          <systemCode>hsas00</systemCode>
          <activities>
            <item>
              <name>Referred to</name>
              <date>2013-04-18T14:01:10Z</date>
            </item>
          </activities>
          <name>Armed Services Committee</name>
          <subcommittees>
            <item>
              <name>Readiness Subcommittee</name>
              <systemCode>hsas03</systemCode>
              <activities>
                <item>
                  <name>Referred to</name>
                  <date>2013-05-06T20:24:17Z</date>
                </item>
              </activities>
            </item>
          </subcommittees>
          <type>Standing</type>
        </item>
      </billCommittees>
    </committees>
    <committeeReports />
    <congress>113</congress>
    <title>Security Clearance Protection Act of 2013</title>
    <notes />
    <originChamber>House</originChamber>
    <cosponsors>
      <item>
        <lastName>Hanabusa</lastName>
        <firstName>Colleen</firstName>
        <bioguideId>H001050</bioguideId>
        <identifiers>
          <lisID>2010</lisID>
          <gpoId>7912</gpoId>
          <bioguideId>H001050</bioguideId>
        </identifiers>
        <fullName>Rep. Hanabusa, Colleen W. [D-HI-1]</fullName>
        <party>D</party>
        <state>HI</state>
        <sponsorshipDate>2013-04-18</sponsorshipDate>
        <middleName>W.</middleName>
        <district>1</district>
        <sponsorshipWithdrawnDate />
        <isOriginalCosponsor>True</isOriginalCosponsor>
      </item>
      <item>
        <lastName>Heck</lastName>
        <firstName>Denny</firstName>
        <bioguideId>H001064</bioguideId>
        <identifiers>
          <bioguideId>H001064</bioguideId>
          <lisID>2170</lisID>
          <gpoId />
        </identifiers>
        <fullName>Rep. Heck, Denny [D-WA-10]</fullName>
        <party>D</party>
        <state>WA</state>
        <sponsorshipDate>2013-04-18</sponsorshipDate>
        <middleName />
        <district>10</district>
        <sponsorshipWithdrawnDate />
        <isOriginalCosponsor>True</isOriginalCosponsor>
      </item>
      <item>
        <lastName>Carson</lastName>
        <firstName>Andre</firstName>
        <bioguideId>C001072</bioguideId>
        <identifiers>
          <lisID>1889</lisID>
          <bioguideId>C001072</bioguideId>
          <gpoId>7946</gpoId>
        </identifiers>
        <fullName>Rep. Carson, Andre [D-IN-7]</fullName>
        <party>D</party>
        <state>IN</state>
        <sponsorshipDate>2013-04-24</sponsorshipDate>
        <middleName />
        <district>7</district>
        <sponsorshipWithdrawnDate />
        <isOriginalCosponsor>False</isOriginalCosponsor>
      </item>
      <item>
        <lastName>Delaney</lastName>
        <firstName>John</firstName>
        <bioguideId>D000620</bioguideId>
        <identifiers>
          <gpoId />
          <lisID>2133</lisID>
          <bioguideId>D000620</bioguideId>
        </identifiers>
        <fullName>Rep. Delaney, John K. [D-MD-6]</fullName>
        <party>D</party>
        <state>MD</state>
        <sponsorshipDate>2013-05-21</sponsorshipDate>
        <middleName>K.</middleName>
        <district>6</district>
        <sponsorshipWithdrawnDate />
        <isOriginalCosponsor>False</isOriginalCosponsor>
      </item>
      <item>
        <lastName>Renacci</lastName>
        <firstName>James</firstName>
        <bioguideId>R000586</bioguideId>
        <identifiers>
          <gpoId>8106</gpoId>
          <lisID>2048</lisID>
          <bioguideId>R000586</bioguideId>
        </identifiers>
        <fullName>Rep. Renacci, James B. [R-OH-16]</fullName>
        <party>R</party>
        <state>OH</state>
        <sponsorshipDate>2013-05-21</sponsorshipDate>
        <middleName>B.</middleName>
        <district>16</district>
        <sponsorshipWithdrawnDate />
        <isOriginalCosponsor>False</isOriginalCosponsor>
      </item>
      <item>
        <lastName>Owens</lastName>
        <firstName>William</firstName>
        <bioguideId>O000169</bioguideId>
        <identifiers>
          <gpoId>8673</gpoId>
          <lisID>1974</lisID>
          <bioguideId>O000169</bioguideId>
        </identifiers>
        <fullName>Rep. Owens, William L. [D-NY-21]</fullName>
        <party>D</party>
        <state>NY</state>
        <sponsorshipDate>2013-05-22</sponsorshipDate>
        <middleName>L.</middleName>
        <district>21</district>
        <sponsorshipWithdrawnDate />
        <isOriginalCosponsor>False</isOriginalCosponsor>
      </item>
    </cosponsors>
    <cboCostEstimates />
    <recordedVotes />
    <actions>
      <actionByCounts>
        <houseOfRepresentatives>4</houseOfRepresentatives>
      </actionByCounts>
      <actionTypeCounts>
        <introducedInTheHouse>1</introducedInTheHouse>
        <placeholderTextForH>1</placeholderTextForH>
        <introducedInHouse>1</introducedInHouse>
        <billReferrals>1</billReferrals>
      </actionTypeCounts>
      <item>
        <actionDate>2013-05-06</actionDate>
        <committee>
          <systemCode>hsas03</systemCode>
          <name>Readiness Subcommittee</name>
        </committee>
        <links />
        <sourceSystem>
          <code>1</code>
          <name>House committee actions</name>
        </sourceSystem>
        <text>Referred to the Subcommittee on Readiness.</text>
        <type>Committee</type>
      </item>
      <item>
        <actionCode>H11100</actionCode>
        <type>IntroReferral</type>
        <links />
        <committee>
          <systemCode>hsas00</systemCode>
          <name>Armed Services Committee</name>
        </committee>
        <actionDate>2013-04-18</actionDate>
        <sourceSystem>
          <code>2</code>
          <name>House floor actions</name>
        </sourceSystem>
        <text>Referred to the House Committee on Armed Services.</text>
      </item>
      <item>
        <actionCode>Intro-H</actionCode>
        <type>IntroReferral</type>
        <links />
        <committee />
        <actionDate>2013-04-18</actionDate>
        <sourceSystem>
          <code>9</code>
          <name>Library of Congress</name>
        </sourceSystem>
        <text>Introduced in House</text>
      </item>
      <item>
        <actionCode>1000</actionCode>
        <type>IntroReferral</type>
        <links />
        <committee />
        <actionDate>2013-04-18</actionDate>
        <sourceSystem>
          <code>9</code>
          <name>Library of Congress</name>
        </sourceSystem>
        <text>Introduced in House</text>
      </item>
    </actions>
    <createDate>2013-04-19T07:02:09Z</createDate>
    <laws />
    <introducedDate>2013-04-18</introducedDate>
    <updateDate>2018-06-05T16:15:38Z</updateDate>
    <policyArea>
      <name>Armed Forces and National Security</name>
    </policyArea>
    <titles>
      <item>
        <titleType>Short Titles as Introduced</titleType>
        <parentTitleType />
        <chamberName />
        <chamberCode />
        <title>Security Clearance Protection Act of 2013</title>
      </item>
      <item>
        <titleType>Official Title as Introduced</titleType>
        <parentTitleType />
        <chamberName />
        <chamberCode />
        <title>To protect the eligibility for Federal employment and access to classified information for Department of Defense civilian employees who may incur financial hardships as a result of furloughs dictated by sequestration.</title>
      </item>
      <item>
        <titleType>Display Title</titleType>
        <parentTitleType />
        <chamberName />
        <chamberCode />
        <title>Security Clearance Protection Act of 2013</title>
      </item>
    </titles>
    <relatedBills />
    <amendments />
    <billNumber>1642</billNumber>
    <calendarNumbers />
  </bill>
  <dublinCore xmlns:dc="http://purl.org/dc/elements/1.1/">
    <dc:format>text/xml</dc:format>
    <dc:language>EN</dc:language>
    <dc:rights>Pursuant to Title 17 Section 105 of the United States Code, this file is not subject to copyright protection and is in the public domain.</dc:rights>
    <dc:contributor>Congressional Research Service, Library of Congress</dc:contributor>
    <dc:description>This file contains bill summaries and statuses for federal legislation. A bill summary describes the most significant provisions of a piece of legislation and details the effects the legislative text may have on current law and federal programs. Bill summaries are authored by the Congressional Research Service (CRS) of the Library of Congress. As stated in Public Law 91-510 (2 USC 166 (d)(6)), one of the duties of CRS is "to prepare summaries and digests of bills and resolutions of a public general nature introduced in the Senate or House of Representatives". For more information, refer to the User Guide that accompanies this file.</dc:description>
  </dublinCore>
</billStatus>

